src/reservoir_computing/__init__.py
src/reservoir_computing/config.py
src/reservoir_computing/config_refactored.py
src/reservoir_computing/core.py
src/reservoir_computing/core_refactored.py
src/reservoir_computing/deep_esn_implementations.py
src/reservoir_computing/echo_state_network.py
src/reservoir_computing/esn_config.py
src/reservoir_computing/pred_modules.py
src/reservoir_computing/utils.py
src/reservoir_computing/utils_refactored.py
src/reservoir_computing/viz.py
src/reservoir_computing/viz_refactored.py
src/reservoir_computing/config_modules/__init__.py
src/reservoir_computing/config_modules/auto_tuning.py
src/reservoir_computing/config_modules/basic_config.py
src/reservoir_computing/config_modules/config_classes.py
src/reservoir_computing/config_modules/config_enums.py
src/reservoir_computing/config_modules/config_factories.py
src/reservoir_computing/config_modules/config_utilities.py
src/reservoir_computing/config_modules/esp_validation.py
src/reservoir_computing/config_modules/optimization_engine.py
src/reservoir_computing/config_modules/performance_analysis.py
src/reservoir_computing/core_modules/__init__.py
src/reservoir_computing/core_modules/core_algorithms.py
src/reservoir_computing/core_modules/core_networks.py
src/reservoir_computing/core_modules/core_theory.py
src/reservoir_computing/core_modules/core_utilities.py
src/reservoir_computing/core_modules/echo_state_network.py
src/reservoir_computing/core_modules/prediction_generation.py
src/reservoir_computing/core_modules/reservoir_initialization.py
src/reservoir_computing/core_modules/reservoir_theory.py
src/reservoir_computing/core_modules/state_updates.py
src/reservoir_computing/core_modules/training_methods.py
src/reservoir_computing/esn_modules/__init__.py
src/reservoir_computing/esn_modules/configuration_advanced.py
src/reservoir_computing/esn_modules/configuration_basic.py
src/reservoir_computing/esn_modules/configuration_helpers.py
reservoir_computing_benedictchen-1.2.2.dist-info/METADATA
reservoir_computing_benedictchen-1.2.2.dist-info/WHEEL
reservoir_computing_benedictchen-1.2.2.dist-info/licenses/LICENSE
reservoir_computing_benedictchen-1.2.2.dist-info/RECORD
